{
  "entrypoints": [
    "main"
  ],
  "origins": {
    "75": [
      532,
      592,
      75
    ],
    "546": [
      89,
      103,
      532,
      558,
      592,
      546
    ],
    "558": [
      89,
      103,
      195,
      514,
      532,
      546,
      592,
      558
    ],
    "17896441": [
      532,
      592,
      918
    ],
    "main": [
      303,
      532,
      179
    ],
    "runtime~main": [
      179,
      532,
      303
    ],
    "02589645": [
      592,
      9
    ],
    "10a2e8c0": [
      592,
      582
    ],
    "1be78505": [
      532,
      558,
      592,
      75
    ],
    "3720c009": [
      532,
      592,
      751
    ],
    "3985f3fe": [
      592,
      61
    ],
    "4d826c8d": [
      592,
      780
    ],
    "517aa66b": [
      592,
      105
    ],
    "55960ee5": [
      121
    ],
    "814f3328": [
      535
    ],
    "935f2afb": [
      53
    ],
    "9e4087bc": [
      532,
      592,
      608
    ],
    "a6aa9e1f": [
      532,
      546,
      558,
      592,
      89
    ],
    "ad7efe8c": [
      592,
      654
    ],
    "b2b675dd": [
      533
    ],
    "b2f554cd": [
      477
    ],
    "b2f90839": [
      592,
      739
    ],
    "bbb095bf": [
      592,
      974
    ],
    "bf9e930a": [
      592,
      48
    ],
    "c4f5d8e4": [
      532,
      558,
      592,
      195
    ],
    "c7a22f1b": [
      592,
      143
    ],
    "ccc49370": [
      532,
      546,
      558,
      592,
      103
    ],
    "dfadc8c2": [
      592,
      744
    ],
    "styles": [
      75,
      89,
      103,
      179,
      195,
      303,
      514,
      546,
      558,
      592,
      608,
      751,
      918,
      532
    ],
    "common": [
      9,
      48,
      61,
      75,
      89,
      103,
      105,
      143,
      195,
      514,
      532,
      546,
      558,
      582,
      608,
      654,
      739,
      744,
      751,
      780,
      918,
      974,
      592
    ]
  },
  "assets": {
    "9": {
      "js": [
        {
          "file": "assets/js/02589645.83f558b4.js",
          "hash": "353d45de8719e0c2a64f",
          "publicPath": "/assets/js/02589645.83f558b4.js"
        }
      ]
    },
    "48": {
      "js": [
        {
          "file": "assets/js/bf9e930a.a977ab6a.js",
          "hash": "092e1b18a3b34b3979ca",
          "publicPath": "/assets/js/bf9e930a.a977ab6a.js"
        }
      ]
    },
    "53": {
      "js": [
        {
          "file": "assets/js/935f2afb.56d08e26.js",
          "hash": "bb88fd056feee6e414c7",
          "publicPath": "/assets/js/935f2afb.56d08e26.js"
        }
      ]
    },
    "61": {
      "js": [
        {
          "file": "assets/js/3985f3fe.8ccf0737.js",
          "hash": "e5b7a581924c1950a6f8",
          "publicPath": "/assets/js/3985f3fe.8ccf0737.js"
        }
      ]
    },
    "75": {
      "js": [
        {
          "file": "assets/js/75.081d9a3e.js",
          "hash": "178949c954eb791e6598",
          "publicPath": "/assets/js/75.081d9a3e.js"
        },
        {
          "file": "assets/js/1be78505.da159ae3.js",
          "hash": "c24592778c71f215daa0",
          "publicPath": "/assets/js/1be78505.da159ae3.js"
        }
      ]
    },
    "89": {
      "js": [
        {
          "file": "assets/js/a6aa9e1f.f1606180.js",
          "hash": "9ec5ad9ca1a91ffd187d",
          "publicPath": "/assets/js/a6aa9e1f.f1606180.js"
        }
      ]
    },
    "103": {
      "js": [
        {
          "file": "assets/js/ccc49370.6d7a3c91.js",
          "hash": "84c86147d7f572b24858",
          "publicPath": "/assets/js/ccc49370.6d7a3c91.js"
        }
      ]
    },
    "105": {
      "js": [
        {
          "file": "assets/js/517aa66b.618affe5.js",
          "hash": "c49ca9ea08ba41fc4114",
          "publicPath": "/assets/js/517aa66b.618affe5.js"
        }
      ]
    },
    "121": {
      "js": [
        {
          "file": "assets/js/55960ee5.55cf7d88.js",
          "hash": "4b1de3421b5d5aef8102",
          "publicPath": "/assets/js/55960ee5.55cf7d88.js"
        }
      ]
    },
    "143": {
      "js": [
        {
          "file": "assets/js/c7a22f1b.6ced128f.js",
          "hash": "4c9811c70eafd1fcd730",
          "publicPath": "/assets/js/c7a22f1b.6ced128f.js"
        }
      ]
    },
    "179": {
      "js": [
        {
          "file": "assets/js/main.8e7c72c4.js",
          "hash": "fbb1d65e56944bd07200",
          "publicPath": "/assets/js/main.8e7c72c4.js"
        }
      ]
    },
    "195": {
      "js": [
        {
          "file": "assets/js/c4f5d8e4.cd4e46d7.js",
          "hash": "773574d403c113f26f4a",
          "publicPath": "/assets/js/c4f5d8e4.cd4e46d7.js"
        }
      ]
    },
    "303": {
      "js": [
        {
          "file": "assets/js/runtime~main.bf7d7306.js",
          "hash": "59f98f3810e617eeedeb",
          "publicPath": "/assets/js/runtime~main.bf7d7306.js"
        }
      ]
    },
    "477": {
      "js": [
        {
          "file": "assets/js/b2f554cd.8e27a9ae.js",
          "hash": "e12a60db648f484e556b",
          "publicPath": "/assets/js/b2f554cd.8e27a9ae.js"
        }
      ]
    },
    "532": {
      "css": [
        {
          "file": "assets/css/styles.90f55e9d.css",
          "hash": "cd10f83ec6c153bdc0ec",
          "publicPath": "/assets/css/styles.90f55e9d.css"
        }
      ]
    },
    "533": {
      "js": [
        {
          "file": "assets/js/b2b675dd.720981bd.js",
          "hash": "1366fe931f83a50068ee",
          "publicPath": "/assets/js/b2b675dd.720981bd.js"
        }
      ]
    },
    "535": {
      "js": [
        {
          "file": "assets/js/814f3328.841240a2.js",
          "hash": "60fcc73209fc77fb52f4",
          "publicPath": "/assets/js/814f3328.841240a2.js"
        }
      ]
    },
    "546": {
      "js": [
        {
          "file": "assets/js/546.dfc069d4.js",
          "hash": "1fb04f36c208f881fd2e",
          "publicPath": "/assets/js/546.dfc069d4.js"
        }
      ]
    },
    "558": {
      "js": [
        {
          "file": "assets/js/558.e8861946.js",
          "hash": "6d0edde8b4d12c8db379",
          "publicPath": "/assets/js/558.e8861946.js"
        }
      ]
    },
    "582": {
      "js": [
        {
          "file": "assets/js/10a2e8c0.7a80177b.js",
          "hash": "8f42e9fe5321e75b7127",
          "publicPath": "/assets/js/10a2e8c0.7a80177b.js"
        }
      ]
    },
    "592": {
      "js": [
        {
          "file": "assets/js/common.2fc1722d.js",
          "hash": "4ebfe461d44bec7491ea",
          "publicPath": "/assets/js/common.2fc1722d.js"
        }
      ]
    },
    "608": {
      "js": [
        {
          "file": "assets/js/9e4087bc.b3b5be17.js",
          "hash": "142416acfcc32e3a35ba",
          "publicPath": "/assets/js/9e4087bc.b3b5be17.js"
        }
      ]
    },
    "654": {
      "js": [
        {
          "file": "assets/js/ad7efe8c.d835b3ae.js",
          "hash": "63d1085a693f31b7479f",
          "publicPath": "/assets/js/ad7efe8c.d835b3ae.js"
        }
      ]
    },
    "739": {
      "js": [
        {
          "file": "assets/js/b2f90839.1f9e46e6.js",
          "hash": "355eefa1d1f6647e7fa6",
          "publicPath": "/assets/js/b2f90839.1f9e46e6.js"
        }
      ]
    },
    "744": {
      "js": [
        {
          "file": "assets/js/dfadc8c2.9ca5892a.js",
          "hash": "94530b904e6cbd903bf4",
          "publicPath": "/assets/js/dfadc8c2.9ca5892a.js"
        }
      ]
    },
    "751": {
      "js": [
        {
          "file": "assets/js/3720c009.0da39538.js",
          "hash": "663aabcdac89db416192",
          "publicPath": "/assets/js/3720c009.0da39538.js"
        }
      ]
    },
    "780": {
      "js": [
        {
          "file": "assets/js/4d826c8d.7fb9de06.js",
          "hash": "bac11a648d0342c7f2c3",
          "publicPath": "/assets/js/4d826c8d.7fb9de06.js"
        }
      ]
    },
    "918": {
      "js": [
        {
          "file": "assets/js/17896441.76fa2199.js",
          "hash": "167e595ef5c459f922a5",
          "publicPath": "/assets/js/17896441.76fa2199.js"
        }
      ]
    },
    "974": {
      "js": [
        {
          "file": "assets/js/bbb095bf.bb567352.js",
          "hash": "541258231404a7196c47",
          "publicPath": "/assets/js/bbb095bf.bb567352.js"
        }
      ]
    }
  }
}